lockss/warcread/__init__.py
lockss/warcread/__main__.py
lockss/warcread/cli.py
lockss/warcread/warcutil.py
lockss_warcread-0.4.0.dist-info/LICENSE
lockss_warcread-0.4.0.dist-info/METADATA
lockss_warcread-0.4.0.dist-info/WHEEL
lockss_warcread-0.4.0.dist-info/entry_points.txt
lockss_warcread-0.4.0.dist-info/RECORD
