Metadata-Version: 2.3
Name: lockss-warcread
Version: 0.4.0
Summary: Library and command line tool for WARC file reporting and processing
License: BSD-3-Clause
Author: Thib Guicherd-Callin
Author-email: thib@cs.stanford.edu
Maintainer: Thib Guicherd-Callin
Maintainer-email: thib@cs.stanford.edu
Requires-Python: >=3.9,<4.0
Classifier: Development Status :: 5 - Production/Stable
Classifier: Environment :: Console
Classifier: Framework :: Pydantic :: 2
Classifier: Intended Audience :: Developers
Classifier: Intended Audience :: System Administrators
Classifier: License :: OSI Approved :: BSD License
Classifier: Programming Language :: Python
Classifier: Topic :: Software Development :: Libraries
Classifier: Topic :: System :: Archiving
Classifier: Topic :: Utilities
Requires-Dist: legacy-cgi (>=2.6.0,<3.0.0)
Requires-Dist: lockss-pybasic (>=0.1.0,<0.2.0)
Requires-Dist: pydantic (>=2.11.0,<3.0.0)
Requires-Dist: pydantic-argparse (>=0.10.0,<0.11.0)
Requires-Dist: warcio (>=1.7.0,<2.0.0)
Project-URL: Repository, https://github.com/lockss/lockss-warcread
